pyTinetSdk-0.2.dist-info/METADATA
pyTinetSdk-0.2.dist-info/RECORD
pyTinetSdk-0.2.dist-info/WHEEL
pyTinetSdk-0.2.dist-info/top_level.txt
tinetclink/Core.py
tinetclink/__init__.py
tinetclink/CallControlAndManage/CallControl.py
tinetclink/CallControlAndManage/CallManage.py
tinetclink/CallControlAndManage/__init__.py
tinetclink/ConfigManage/Agent.py
tinetclink/ConfigManage/IVRSetting.py
tinetclink/ConfigManage/Number.py
tinetclink/ConfigManage/Phone.py
tinetclink/ConfigManage/Queue.py
tinetclink/ConfigManage/__init__.py
tinetclink/RecordsQuery/CalledLog.py
tinetclink/RecordsQuery/CallinLog.py
tinetclink/RecordsQuery/Comment.py
tinetclink/RecordsQuery/Investigation.py
tinetclink/RecordsQuery/Record.py
tinetclink/RecordsQuery/__init__.py
tinetclink/SystemSupervision/AgentStatus.py
tinetclink/SystemSupervision/__init__.py
