Metadata-Version: 2.1
Name: pyTinetSdk
Version: 0.2
Summary: 第三方天润融通PythonSDK
Home-page: https://github.com/blacklin/pyTinetSdk
Author: blacklin
Author-email: admin@bigbba.com
License: UNKNOWN
Platform: UNKNOWN
Requires: requests
